{
  "job": "Adsorption / Ni_Cu_ads",
  "last_update": "2026-03-11T17:46:16.374973",
  "status": "finished",
  "latest_energy_ry": -8184.63596654,
  "num_energy_points": 8,
  "latest_total_force_ry_bohr": 0.038025,
  "target_total_force_ry_bohr": null,
  "num_total_force_points": 8,
  "latest_gradient_error_ry_bohr": 0.018,
  "target_gradient_error_ry_bohr": null,
  "num_gradient_error_points": 8,
  "bfgs_steps": 7,
  "scf_cycles": 8,
  "converged": true,
  "positions_format": "ATOMIC_POSITIONS (angstrom)",
  "cell_format": "crystal axes from output header",
  "cell_source": "output_header",
  "nat_latest": 86,
  "num_structure_steps": 8,
  "xyz_units": "angstrom"
}