{
  "job": "Ni-Ag-Glu_(FOCUS)",
  "last_update": "2026-06-13T11:16:13.665457",
  "status": "running",
  "latest_energy_ry": -11738.29927663,
  "num_energy_points": 60,
  "latest_total_force_ry_bohr": 0.007842,
  "target_total_force_ry_bohr": null,
  "num_total_force_points": 60,
  "latest_gradient_error_ry_bohr": 0.0016,
  "target_gradient_error_ry_bohr": null,
  "num_gradient_error_points": 60,
  "bfgs_steps": 59,
  "scf_cycles": 60,
  "converged": true,
  "job_done": false,
  "positions_format": "ATOMIC_POSITIONS (angstrom)",
  "cell_format": "crystal axes from output header",
  "cell_source": "output_header",
  "nat_latest": 146,
  "num_structure_steps": 60,
  "xyz_units": "angstrom"
}