{
  "job": "Ni-Ag-Glu_(FOCUS)",
  "last_update": "2026-06-13T22:26:10.115257",
  "status": "running",
  "latest_energy_ry": -11738.34098402,
  "num_energy_points": 35,
  "latest_total_force_ry_bohr": 0.00632,
  "target_total_force_ry_bohr": null,
  "num_total_force_points": 35,
  "latest_gradient_error_ry_bohr": 0.0015,
  "target_gradient_error_ry_bohr": null,
  "num_gradient_error_points": 35,
  "bfgs_steps": 34,
  "scf_cycles": 35,
  "converged": true,
  "job_done": false,
  "positions_format": "ATOMIC_POSITIONS (angstrom)",
  "cell_format": "crystal axes from output header",
  "cell_source": "output_header",
  "nat_latest": 146,
  "num_structure_steps": 35,
  "xyz_units": "angstrom"
}