{
  "job": "Ni-Ag_(DONE)",
  "last_update": "2026-06-09T15:30:52.516040",
  "status": "running",
  "latest_energy_ry": -5914.20179689,
  "num_energy_points": 23,
  "latest_total_force_ry_bohr": 0.088905,
  "target_total_force_ry_bohr": null,
  "num_total_force_points": 23,
  "latest_gradient_error_ry_bohr": 0.016,
  "target_gradient_error_ry_bohr": null,
  "num_gradient_error_points": 23,
  "bfgs_steps": 22,
  "scf_cycles": 23,
  "converged": true,
  "job_done": false,
  "positions_format": "ATOMIC_POSITIONS (angstrom)",
  "cell_format": "crystal axes from output header",
  "cell_source": "output_header",
  "nat_latest": 64,
  "num_structure_steps": 23,
  "xyz_units": "angstrom"
}