{
  "job": "NEB / Ni_Gl_HOH_FS",
  "last_update": "2026-07-15T15:37:45.140443",
  "status": "running",
  "latest_energy_ry": -6614.59783759,
  "num_energy_points": 51,
  "latest_total_force_ry_bohr": 0.02939,
  "target_total_force_ry_bohr": null,
  "num_total_force_points": 51,
  "latest_gradient_error_ry_bohr": 0.011,
  "target_gradient_error_ry_bohr": null,
  "num_gradient_error_points": 51,
  "latest_scf_accuracy_ry": 0.00022489,
  "num_scf_accuracy_points": 2115,
  "latest_conv_thr_ry": 1.04e-08,
  "num_conv_thr_points": 51,
  "latest_total_magnetization_bohr_cell": 39.67,
  "num_total_magnetization_points": 2115,
  "bfgs_steps": 49,
  "scf_cycles": 51,
  "converged": true,
  "job_done": false,
  "positions_format": "ATOMIC_POSITIONS (angstrom)",
  "cell_format": "crystal axes from output header",
  "cell_source": "output_header",
  "nat_latest": 80,
  "num_structure_steps": 51,
  "xyz_units": "angstrom"
}