{
  "job": "NEB / Ni_Gl_HOH_FS",
  "last_update": "2026-07-15T14:55:12.401708",
  "status": "running",
  "latest_energy_ry": -6614.59180988,
  "num_energy_points": 42,
  "latest_total_force_ry_bohr": 0.012658,
  "target_total_force_ry_bohr": null,
  "num_total_force_points": 42,
  "latest_gradient_error_ry_bohr": 0.0066,
  "target_gradient_error_ry_bohr": null,
  "num_gradient_error_points": 42,
  "latest_scf_accuracy_ry": 2e-08,
  "num_scf_accuracy_points": 1730,
  "latest_conv_thr_ry": 2.6e-09,
  "num_conv_thr_points": 42,
  "latest_total_magnetization_bohr_cell": 39.82,
  "num_total_magnetization_points": 1730,
  "bfgs_steps": 40,
  "scf_cycles": 42,
  "converged": true,
  "job_done": false,
  "positions_format": "ATOMIC_POSITIONS (angstrom)",
  "cell_format": "crystal axes from output header",
  "cell_source": "output_header",
  "nat_latest": 80,
  "num_structure_steps": 42,
  "xyz_units": "angstrom"
}