{
  "job": "Ni-Ag-Glu-OH-2",
  "last_update": "2026-06-29T17:28:04.578358",
  "status": "running",
  "latest_energy_ry": -11771.8621215,
  "num_energy_points": 35,
  "latest_total_force_ry_bohr": 0.008641,
  "target_total_force_ry_bohr": null,
  "num_total_force_points": 35,
  "latest_gradient_error_ry_bohr": 0.0025,
  "target_gradient_error_ry_bohr": null,
  "num_gradient_error_points": 35,
  "latest_scf_accuracy_ry": 4.2e-07,
  "num_scf_accuracy_points": 1281,
  "latest_conv_thr_ry": 3.4e-09,
  "num_conv_thr_points": 35,
  "latest_total_magnetization_bohr_cell": 43.0,
  "num_total_magnetization_points": 1281,
  "bfgs_steps": 34,
  "scf_cycles": 35,
  "converged": true,
  "job_done": false,
  "positions_format": "ATOMIC_POSITIONS (angstrom)",
  "cell_format": "crystal axes from output header",
  "cell_source": "output_header",
  "nat_latest": 148,
  "num_structure_steps": 35,
  "xyz_units": "angstrom"
}