{
  "job": "NEB / Ni_Gl_HOH_FS_2",
  "last_update": "2026-07-20T22:28:01.439698",
  "status": "running",
  "latest_energy_ry": -6614.58170315,
  "num_energy_points": 102,
  "latest_total_force_ry_bohr": 0.019064,
  "target_total_force_ry_bohr": null,
  "num_total_force_points": 102,
  "latest_gradient_error_ry_bohr": 0.012,
  "target_gradient_error_ry_bohr": null,
  "num_gradient_error_points": 102,
  "latest_scf_accuracy_ry": 0.00049609,
  "num_scf_accuracy_points": 4119,
  "latest_conv_thr_ry": 2.7e-09,
  "num_conv_thr_points": 102,
  "latest_total_magnetization_bohr_cell": 39.87,
  "num_total_magnetization_points": 4119,
  "bfgs_steps": 100,
  "scf_cycles": 102,
  "converged": true,
  "job_done": false,
  "positions_format": "ATOMIC_POSITIONS (angstrom)",
  "cell_format": "crystal axes from output header",
  "cell_source": "output_header",
  "nat_latest": 80,
  "num_structure_steps": 102,
  "xyz_units": "angstrom"
}