{
  "job": "NEB / Ni_Gl_HOH_FS_2",
  "last_update": "2026-07-21T17:53:18.714681",
  "status": "running",
  "latest_energy_ry": -6614.62818533,
  "num_energy_points": 37,
  "latest_total_force_ry_bohr": 0.015528,
  "target_total_force_ry_bohr": null,
  "num_total_force_points": 37,
  "latest_gradient_error_ry_bohr": 0.0059,
  "target_gradient_error_ry_bohr": null,
  "num_gradient_error_points": 37,
  "latest_scf_accuracy_ry": 1.7e-07,
  "num_scf_accuracy_points": 1442,
  "latest_conv_thr_ry": 3.7e-09,
  "num_conv_thr_points": 37,
  "latest_total_magnetization_bohr_cell": 40.11,
  "num_total_magnetization_points": 1442,
  "bfgs_steps": 35,
  "scf_cycles": 37,
  "converged": true,
  "job_done": false,
  "positions_format": "ATOMIC_POSITIONS (angstrom)",
  "cell_format": "crystal axes from output header",
  "cell_source": "output_header",
  "nat_latest": 80,
  "num_structure_steps": 37,
  "xyz_units": "angstrom"
}