{
  "job": "Adsorption / Ni-OH",
  "last_update": "2026-04-05T06:37:46.174927",
  "status": "finished",
  "latest_energy_ry": -3654.07821968,
  "num_energy_points": 76,
  "latest_total_force_ry_bohr": 0.00708,
  "target_total_force_ry_bohr": null,
  "num_total_force_points": 76,
  "latest_gradient_error_ry_bohr": 0.0022,
  "target_gradient_error_ry_bohr": null,
  "num_gradient_error_points": 76,
  "bfgs_steps": 75,
  "scf_cycles": 76,
  "converged": true,
  "positions_format": "ATOMIC_POSITIONS (angstrom)",
  "cell_format": "crystal axes from output header",
  "cell_source": "output_header",
  "nat_latest": 38,
  "num_structure_steps": 76,
  "xyz_units": "angstrom"
}