{
  "input_file": "/media/node1/Fairus2TB/fairus/Nguyen/SCF/Ni/input.pw.x",
  "input_file_name": "input.pw.x",
  "parameters": {
    "occupations": "smearing",
    "degauss": "0.02",
    "nspin": "1",
    "nosym": ".false.",
    "noinv": ".false.",
    "noncolin": ".false.",
    "vdw_corr": "grimme-d3",
    "conv_thr": "1e-07",
    "electron_maxstep": "200",
    "mixing_beta": "0.04",
    "mixing_mode": "plain",
    "scf_must_converge": ".TRUE.",
    "startingwfc": null,
    "forc_conv_thr": "1d-3"
  },
  "all_parameters": {
    "calculation": "scf",
    "forc_conv_thr": "1d-3",
    "nstep": "200",
    "outdir": "./output/",
    "prefix": "VLAB",
    "pseudo_dir": "/home/node1/PSP/PseudosP/pslibrary-master/pbe/PSEUDOPOTENTIALS/",
    "restart_mode": "from_scratch",
    "tprnfor": ".TRUE.",
    "verbosity": "high",
    "wf_collect": ".TRUE.",
    "ibrav": "0",
    "nat": "72",
    "ntyp": "4",
    "ecutwfc": "50",
    "ecutrho": "400",
    "occupations": "smearing",
    "degauss": "0.02",
    "nspin": "1",
    "nosym": ".false.",
    "noinv": ".false.",
    "noncolin": ".false.",
    "vdw_corr": "grimme-d3",
    "conv_thr": "1e-07",
    "electron_maxstep": "200",
    "mixing_beta": "0.04",
    "mixing_mode": "plain",
    "scf_must_converge": ".TRUE."
  },
  "text": "&CONTROL\ncalculation = 'scf'\nforc_conv_thr = 1d-3\nnstep = 200\noutdir = './output/'\nprefix = 'VLAB'\npseudo_dir = '/home/node1/PSP/PseudosP/pslibrary-master/pbe/PSEUDOPOTENTIALS/'\nrestart_mode = 'from_scratch'\ntprnfor = .TRUE.\nverbosity = 'high'\nwf_collect = .TRUE.\n/\n&SYSTEM\n ibrav = 0\n nat = 72\n ntyp = 4\n\n ecutwfc = 50\n ecutrho = 400\n\n occupations = 'smearing'\n degauss = 0.02\n\n nspin = 1\n\n\n nosym = .false.\n noinv = .false.\n noncolin = .false.\n\n vdw_corr = 'grimme-d3'\n/\n&ELECTRONS\nconv_thr = 1e-07\nelectron_maxstep = 200\nmixing_beta = 0.04\nmixing_mode = 'plain'\nscf_must_converge = .TRUE.\n!startingwfc = 'random'\n/\n\nATOMIC_SPECIES\nNi 58.7    Ni.pbe-n-rrkjus_psl.1.0.0.UPF\n\n\nK_POINTS {automatic}\n3 3 1 0 0 0\n\n\nCELL_PARAMETERS angstrom\n  7.371900000   0.000000000   0.000000000\n  3.685947771   6.384253961   0.000000000\n  0.000007169  -0.000004139  41.076510000\n\nATOMIC_POSITIONS (angstrom)\nNi               1.2286390390        0.7093535490        9.0125970590    0   0   0\nNi               2.4572760100        2.8374169220        9.0125970590    0   0   0\nNi               3.6859498400        4.9655441370        9.0125970590    0   0   0\nNi               3.6859144660        0.7093535490        9.0125970590    0   0   0\nNi               4.9145514370        2.8374169220        9.0125970590    0   0   0\nNi               6.1432252670        4.9655441370        9.0125970590    0   0   0\nNi               6.1432636120        0.7093535490        9.0125970590    0   0   0\nNi               7.3719005830        2.8374169220        9.0125970590    0   0   0\nNi               8.6005744130        4.9655441370        9.0125970590    0   0   0\nNi               0.0000019230       -0.0000011100       11.0191845730    0   0   0\nNi               1.2286511800        2.1280835430       11.0191845730    0   0   0\nNi               2.4573004380        4.2561681970       11.0191845730    0   0   0\nNi               2.4573019230       -0.0000011100       11.0191845730    0   0   0\nNi               3.6859511800        2.1280835430       11.0191845730    0   0   0\nNi               4.9146004380        4.2561681970       11.0191845730    0   0   0\nNi               4.9146019230       -0.0000011100       11.0191845730    0   0   0\nNi               6.1432511800        2.1280835430       11.0191845730    0   0   0\nNi               7.3719004380        4.2561681970       11.0191845730    0   0   0\nNi               9.8291970100        5.6748892401       13.0324849556    0   0   0\nNi               4.9145980198        5.6748893593       13.0324852164    0   0   0\nNi               7.3718991758        1.4187202853       13.0324856500    0   0   0\nNi               8.6005492460        3.5468057814       13.0324864151    0   0   0\nNi               7.3718984520        5.6748900664       13.0324864346    0   0   0\nNi               2.4573016324        1.4187213286       13.0324867123    0   0   0\nNi               3.6859500153        3.5468058594       13.0324876950    0   0   0\nNi               6.1432488122        3.5468055587       13.0324879319    0   0   0\nNi               4.9146003559        1.4187209547       13.0324881305    0   0   0\nNi               4.9146024517        2.8374451427       15.0334585589    0   0   0\nNi               2.4573039655        2.8374470172       15.0334598186    0   0   0\nNi               6.1432518675        4.9655284072       15.0334598528    0   0   0\nNi               7.3719008977        2.8374462771       15.0334599804    0   0   0\nNi               3.6859555058        0.7093603620       15.0334602556    0   0   0\nNi               1.2286550209        0.7093609929       15.0334616076    0   0   0\nNi               3.6859521613        4.9655297045       15.0334616685    0   0   0\nNi               8.6005513471        4.9655301153       15.0334618667    0   0   0\nNi               6.1432529377        0.7093606827       15.0334623189    0   0   0\nNi               7.3718981461        4.2561658701       17.0436126492    0   0   0\nNi               2.4573001516        4.2561668027       17.0436139163    0   0   0\nNi               4.9146014848       -0.0000023770       17.0436145683    0   0   0\nNi               4.9146006221        4.2561672435       17.0436152860    0   0   0\nNi               0.0000023638       -0.0000021113       17.0436153847    0   0   0\nNi               6.1432512178        2.1280823767       17.0436158106    0   0   0\nNi               1.2286541909        2.1280837412       17.0436166733    0   0   0\nNi               2.4573047358       -0.0000005294       17.0436167517    0   0   0\nNi               3.6859557290        2.1280847607       17.0436183569    0   0   0\nNi               7.3682324909        1.4238082748       19.0376153649\nNi               9.8185310352        5.6692828056       19.0367330591\nNi               2.4511291241        1.4144258654       19.0372660910\nNi               4.9186011880        5.6689726620       19.0342681457\nNi               4.9161224563        1.4127899854       19.0394236046\nNi               3.6834282708        3.5486854913       19.0398948119\nNi               7.3674022105        5.6813374283       19.0467069033\nNi               8.6051491423        3.5399555265       19.0519054803\nNi               6.1312233341        3.5372694084       19.0468198179\nNi               4.8699497787        2.8081972793       21.0685401342\nNi               6.1487642378        4.9449802539       21.0487864580\nNi               3.6811685707        4.9719049312       21.0280507882\nNi               3.6792768815        0.7503237726       21.0672581407\nNi               2.4899029782        2.8084344009       21.0693784816\nNi               1.2138211727        0.6983010321       21.0287063827\nNi               7.3627405697        2.8472556441       21.0547990578\nNi               6.1483037492        0.6970240546       21.0355789587\nNi               8.5768517906        4.9569835923       21.0632870800\nNi               3.6838184573        2.1237163659       23.3836329169\nNi               1.1969392661        2.1154689856       22.9683220768\nNi               2.4486308584        4.2694393023       22.9687060989\nNi               6.1319308981        2.1165377360       22.9938004954\nNi              -0.0075835192       -0.0108679129       23.0438964892\nNi               2.4350629188       -0.0271334279       22.9610514791\nNi               7.3616949483        4.2440198583       23.0373344814\nNi               4.9023030034        4.2531970025       22.9854325487\nNi               4.9095059136        0.0036000375       22.9856889230\n"
}